{"id":"77354722","premium":false,"billing_type":{"id":"standard","name":"Стандарт"},"relations":[],"name":"Инженер IT инфраструктуры","insider_interview":null,"response_letter_required":false,"area":{"id":"1002","name":"Минск","url":"https://api.hh.ru/areas/1002?host=hh.ru"},"salary":null,"type":{"id":"open","name":"Открытая"},"address":null,"allow_messages":true,"experience":{"id":"between1And3","name":"От 1 года до 3 лет"},"schedule":{"id":"fullDay","name":"Полный день"},"employment":{"id":"full","name":"Полная занятость"},"department":null,"contacts":null,"description":"<p><strong>Мобильный оператор life:) расширяет команду IT инфраструктуры. Если вы увлечены IT-технологиями и ищете новые возможности для развития своей карьеры, вакансия для вас! </strong></p> <p><strong>Обязанности:</strong></p> <p>1. Управление жизненным циклом и емкостями IT инфраструктуры:</p> <ul> <li>Capability management IT инфраструктуры мобильного оператора (OSS, BSS, CN), VMware (vSphere, NSX), SAN сети, хранилищ, инфраструктуры резервного копирования (Microfocus DataProtector, Veeam B&amp;R), а так же серверов ОС (Linus, HP-UX, Solaris, Microsoft), Microsoft решений (Exchange, TMG, UAG, Sharepoint и др.);</li> <li>Настройка системы метрик, сбор и анализ KPI IT инфраструктуры.</li> </ul> <p>2. Проектное управление:</p> <ul> <li>Управление инфраструктурными проектами;</li> <li>Координация корпоративных проектов и интеграции систем;</li> <li>Сбор требования к продукту от различных подразделений компании.</li> </ul> <p>3. Планирование:</p> <ul> <li>Разработка дизайнов систем;</li> <li>Участие в разработке новых контрактов на поставку, контрактов на техподдержку и SLA;</li> <li>Анализ roadmap и life cycle документов с целью подготовки предложений о внедрении новых функций и услуг;</li> <li>Участие в разработке стратегии развития, детальном проектирование новых функций, технологий и платформ;</li> <li>Составление RFI, RFP и пр. тех. документации для проведения тендера. Проведение оценки предложений поставщиков.</li> </ul> <p>4. Бюджетирование:</p> <ul> <li>Подготовка и предоставление к согласованию годовых планов OPEX/CAPEX. Ведение бюджета IT infra;</li> <li>Подготовка и обоснование инвестиций.</li> </ul> <p><strong>Требования:</strong></p> <ul> <li>Понимание принципов, технологий и протоколов, применяемых при планировании IT инфраструктуры ЦОД;</li> <li>Опыт использования метрик мониторинга утилизации IT инфраструктуры в продуктах Zabbix, Prometeus, опыт управления жизненным циклом IT систем, гипервизоров и сопровождающих инфраструктурных сервисов;</li> <li>Расчет и анализ требований к iT инфраструктуре со стороны новых продуктов и сервисов, прогнозируемого роста нагрузки;</li> <li>Опыт работы с поставщиками инфраструктурных IT решений: написание технических заданий, опыт в проведении технической оценки спецификаций оборудования и программного обеспечения и расчёта стоимости владения;</li> <li>Опыт выбора и внедрения ИТ-решений для построения высокопроизводительных отказоустойчивых вычислительных систем и систем хранения данных, умение сделать анализ и рассчитать стоимость возможных вариантов и архитектурных решений, умение обосновать решения;</li> <li>Знание основ построения высокопроизводительных SAN сетей, опыт работы с активным сетевым оборудованием.</li> </ul> <p><strong>Мы предлагаем:</strong></p> <ul> <li>Конкурентную заработную плату и ежегодный бонус за результативность;</li> <li>Поддержку профессионального роста и обучение новым технологиям;</li> <li>Офис на ул. Искалиева;</li> <li>Предоставление мобильного телефона;</li> <li>Оплата мобильной связи;</li> <li>Курсы английского языка;</li> <li>Медицинское страхование;</li> <li>Работу в дружной команде профессионалов!</li> </ul> <p><strong><em>Если вы являетесь экспертом в области IT инфраструктуры и хотите работать в динамичной и перспективной команде, то ждем ваши резюме!</em></strong></p>","branded_description":null,"vacancy_constructor_template":{"id":26252,"name":"Брендированный шаблон 1","top_picture":{"height":634,"width":1740,"path":"https://hhcdn.ru/branding-pictures/964529.jpeg","blurred_path":"https://hhcdn.ru/branding-pictures-blurred/964531.jpeg"},"bottom_picture":{"height":320,"width":700,"path":"https://hhcdn.ru/branding-pictures/964546.jpeg","blurred_path":"https://hhcdn.ru/branding-pictures-blurred/964548.jpeg"}},"key_skills":[],"accept_handicapped":false,"accept_kids":false,"archived":false,"response_url":null,"specializations":[],"professional_roles":[{"id":"40","name":"Другое"}],"code":null,"hidden":false,"quick_responses_allowed":false,"driver_license_types":[],"accept_incomplete_resumes":false,"employer":{"id":"590484","name":"БеСТ","url":"https://api.hh.ru/employers/590484?host=hh.ru","alternate_url":"https://hh.ru/employer/590484","logo_urls":{"240":"https://hhcdn.ru/employer-logo/2944689.png","90":"https://hhcdn.ru/employer-logo/2944688.png","original":"https://hhcdn.ru/employer-logo-original/625884.png"},"vacancies_url":"https://api.hh.ru/vacancies?employer_id=590484&host=hh.ru","trusted":true},"published_at":"2023-04-13T16:14:30+0300","created_at":"2023-04-13T16:14:30+0300","initial_created_at":"2023-02-23T14:46:02+0300","negotiations_url":null,"suitable_resumes_url":null,"apply_alternate_url":"https://hh.ru/applicant/vacancy_response?vacancyId=77354722","has_test":false,"test":null,"alternate_url":"https://hh.ru/vacancy/77354722","working_days":[],"working_time_intervals":[],"working_time_modes":[],"accept_temporary":false,"languages":[]}