{"id":"78277526","premium":false,"billing_type":{"id":"standard","name":"Стандарт"},"relations":[],"name":"Главный инженер проекта (ГИП)","insider_interview":null,"response_letter_required":false,"area":{"id":"1002","name":"Минск","url":"https://api.hh.ru/areas/1002?host=hh.ru"},"salary":null,"type":{"id":"open","name":"Открытая"},"address":{"city":"Минск","street":"Пинская улица","building":"28А","lat":53.906379,"lng":27.516799,"description":null,"raw":"Минск, Пинская улица, 28А","metro":{"station_name":"Молодежная","line_name":"Автозаводская","station_id":"63.420","line_id":"63","lat":53.906527,"lng":27.521308},"metro_stations":[{"station_name":"Молодежная","line_name":"Автозаводская","station_id":"63.420","line_id":"63","lat":53.906527,"lng":27.521308}]},"allow_messages":true,"experience":{"id":"moreThan6","name":"Более 6 лет"},"schedule":{"id":"fullDay","name":"Полный день"},"employment":{"id":"full","name":"Полная занятость"},"department":null,"contacts":null,"description":"<p>Развивающаяся компания ООО &quot;Проект-М&quot; (10 лет на рынке проектирования) расширяет свой штат и нуждается в Главном инженере проекта (ГИП) для работы по объектам жилищно-гражданского и производственного назначения (2-4 классов сложности) . Если вы хотите стать частью дружного коллектива , желаете развиваться , обучаться в области BIM-моделирования и достойно зарабатывать - ждем Вас!</p> <p> </p> <p><strong>Обязанности:</strong></p> <ul> <li>Постановка задач и контроль исполнения главным специалистам проектных отделов по объектам гражданского и промышленного назначения; ·</li> <li>Соблюдение графика прохождения документации, взаимного согласования проектных решений инженерно-техническими работниками различных подразделений; ·</li> <li>Согласование, работа с экспертизой и заинтересованными службами;</li> <li>Проведение встреч с заказчиком , участие в тендерах и переговорах; ·</li> <li>Участие в проведении авторского надзора;</li> </ul> <p> </p> <strong>Требования:</strong> <ul> <li>Высшее техническое образование; ·</li> <li>Опыт работы в проектной организации от 8-ти лет; ·</li> <li>Уверенное владение нормативной документацией; ·</li> <li>Приветствуются навыки разработки смет ПИР; ·</li> <li>Умение работать самостоятельно, стремление самостоятельно принимать проектные решения; ·</li> <li>Гибкость в работе, готовность искать варианты решения проблем и предлагать их на согласование;</li> <li>Обязательно знание AutoCad.</li> </ul> <p> </p> <strong>Условия:</strong> <ul> <li>работа в современном офисе, последнее ПО и ПВМ;</li> <li>достойный уровень заработной платы: оклад + KPI, без потолка;</li> <li><strong>обучение Revit;</strong></li> <li><strong>корпоративное обучение английскому языку;</strong></li> <li>гибкий график работы;</li> <li>возможность карьерного роста внутри компании;</li> <li>адекватное и справедливое руководство, молодой и дружный коллектив с горящими глазами (средний возраст 28 лет);</li> <li>чай, кофе за счет организации;</li> <li><strong>вы сможете участвовать в активной корпоративной жизни за счет компании. Вас</strong><strong> будет окружать драйвовый коллектив вместе плаваем на байдарках, сноубордах и просто круто проводить время.</strong></li> </ul>","branded_description":null,"vacancy_constructor_template":null,"key_skills":[],"accept_handicapped":false,"accept_kids":false,"archived":false,"response_url":null,"specializations":[],"professional_roles":[{"id":"48","name":"Инженер-конструктор, инженер-проектировщик"}],"code":null,"hidden":false,"quick_responses_allowed":false,"driver_license_types":[],"accept_incomplete_resumes":false,"employer":{"id":"1439427","name":"Проект-М","url":"https://api.hh.ru/employers/1439427?host=hh.ru","alternate_url":"https://hh.ru/employer/1439427","logo_urls":null,"vacancies_url":"https://api.hh.ru/vacancies?employer_id=1439427&host=hh.ru","trusted":true},"published_at":"2023-03-20T13:25:42+0300","created_at":"2023-03-20T13:25:42+0300","initial_created_at":"2023-03-20T13:25:42+0300","negotiations_url":null,"suitable_resumes_url":null,"apply_alternate_url":"https://hh.ru/applicant/vacancy_response?vacancyId=78277526","has_test":false,"test":null,"alternate_url":"https://hh.ru/vacancy/78277526","working_days":[],"working_time_intervals":[],"working_time_modes":[],"accept_temporary":false,"languages":[]}