{"id":"79063090","premium":false,"billing_type":{"id":"standard","name":"Стандарт"},"relations":[],"name":"Машинист сцены/инженер","insider_interview":null,"response_letter_required":false,"area":{"id":"1002","name":"Минск","url":"https://api.hh.ru/areas/1002?host=hh.ru"},"salary":{"from":700,"to":null,"currency":"BYR","gross":false},"type":{"id":"open","name":"Открытая"},"address":{"city":"Минск","street":"улица Фрунзе","building":"5","lat":53.906034,"lng":27.574605,"description":null,"raw":"Минск, улица Фрунзе, 5","metro":{"station_name":"Площадь Победы","line_name":"Московская","station_id":"62.409","line_id":"62","lat":53.908644,"lng":27.575054},"metro_stations":[{"station_name":"Площадь Победы","line_name":"Московская","station_id":"62.409","line_id":"62","lat":53.908644,"lng":27.575054}]},"allow_messages":true,"experience":{"id":"between1And3","name":"От 1 года до 3 лет"},"schedule":{"id":"fullDay","name":"Полный день"},"employment":{"id":"full","name":"Полная занятость"},"department":null,"contacts":null,"description":"<strong>Обязанности:</strong> <ul> <li>установка декораций и мебели на сцене и в репетиционных помещениях, подвеска мягких декораций, перестановка декораций во время антрактов и частых перемен в соответствии с указаниями заведующего художественно-постановочной частью</li> <li>мелкий ремонт и содержание в чистоте декораций и сценического имущества;</li> <li>выполнение погрузочно-разгрузочных работ по перевозке декораций и сценического имущества на стационаре, выездных спектаклях и гастролях.</li> </ul> <strong>Требования:</strong> <ul> <li>ответственность, коммуникабельность</li> </ul> <strong>Условия:</strong> <ul> <li>молодой и дружный коллектив;</li> <li>перспектива карьерного роста.</li> </ul> <p>Заработная плата от 700 руб. в зависимости от занятости и по итогам собеседования.</p>","branded_description":null,"vacancy_constructor_template":null,"key_skills":[{"name":"Материальная ответственность"},{"name":"Ответственность"},{"name":"Аналитическое мышление"},{"name":"Работа в команде"}],"accept_handicapped":false,"accept_kids":false,"archived":false,"response_url":null,"specializations":[],"professional_roles":[{"id":"40","name":"Другое"}],"code":null,"hidden":false,"quick_responses_allowed":false,"driver_license_types":[],"accept_incomplete_resumes":false,"employer":{"id":"1841309","name":"Театральная мастерская Наталии Башевой","url":"https://api.hh.ru/employers/1841309?host=hh.ru","alternate_url":"https://hh.ru/employer/1841309","logo_urls":{"90":"https://hhcdn.ru/employer-logo/1787394.jpeg","original":"https://hhcdn.ru/employer-logo-original/336282.jpg"},"vacancies_url":"https://api.hh.ru/vacancies?employer_id=1841309&host=hh.ru","trusted":true},"published_at":"2023-04-08T12:03:08+0300","created_at":"2023-04-08T12:03:08+0300","initial_created_at":"2023-04-08T12:03:08+0300","negotiations_url":null,"suitable_resumes_url":null,"apply_alternate_url":"https://hh.ru/applicant/vacancy_response?vacancyId=79063090","has_test":false,"test":null,"alternate_url":"https://hh.ru/vacancy/79063090","working_days":[],"working_time_intervals":[],"working_time_modes":[],"accept_temporary":false,"languages":[]}